[
  {
    "engine": "pmd-custom",
    "fileName": "/Users/lbuthman/Developer/IdeaProjects/buttons-and-more/force-app/main/default/classes/InvestmentCreationHandler.cls",
    "violations": [
      {
        "line": 4,
        "column": 34,
        "endLine": 121,
        "endColumn": 5,
        "severity": 3,
        "ruleName": "NcssMethodCount",
        "category": "Design",
        "url": "https://pmd.github.io/pmd-6.55.0/pmd_rules_apex_design.html#ncssmethodcount",
        "message": "\nThe method 'createInvestment()' has an NCSS line count of 71\n"
      },
      {
        "line": 4,
        "column": 34,
        "endLine": 121,
        "endColumn": 5,
        "severity": 3,
        "ruleName": "CognitiveComplexity",
        "category": "Design",
        "url": "https://pmd.github.io/pmd-6.55.0/pmd_rules_apex_design.html#cognitivecomplexity",
        "message": "\nThe method 'createInvestment(List<InvestmentCreationHandler.RequestPayload>)' has a cognitive complexity of 38, current threshold is 15\n"
      },
      {
        "line": 4,
        "column": 34,
        "endLine": 121,
        "endColumn": 5,
        "severity": 3,
        "ruleName": "CyclomaticComplexity",
        "category": "Design",
        "url": "https://pmd.github.io/pmd-6.55.0/pmd_rules_apex_design.html#cyclomaticcomplexity",
        "message": "\nThe method 'createInvestment(List<InvestmentCreationHandler.RequestPayload>)' has a cyclomatic complexity of 28.\n"
      },
      {
        "line": 56,
        "column": 24,
        "endLine": 56,
        "endColumn": 28,
        "severity": 3,
        "ruleName": "AvoidDebugStatements",
        "category": "Performance",
        "url": "https://pmd.github.io/pmd-6.55.0/pmd_rules_apex_performance.html#avoiddebugstatements",
        "message": "\nAvoid debug statements since they impact on performance\n"
      },
      {
        "line": 57,
        "column": 24,
        "endLine": 57,
        "endColumn": 28,
        "severity": 3,
        "ruleName": "AvoidDebugStatements",
        "category": "Performance",
        "url": "https://pmd.github.io/pmd-6.55.0/pmd_rules_apex_performance.html#avoiddebugstatements",
        "message": "\nAvoid debug statements since they impact on performance\n"
      },
      {
        "line": 58,
        "column": 24,
        "endLine": 58,
        "endColumn": 28,
        "severity": 3,
        "ruleName": "AvoidDebugStatements",
        "category": "Performance",
        "url": "https://pmd.github.io/pmd-6.55.0/pmd_rules_apex_performance.html#avoiddebugstatements",
        "message": "\nAvoid debug statements since they impact on performance\n"
      },
      {
        "line": 59,
        "column": 24,
        "endLine": 59,
        "endColumn": 28,
        "severity": 3,
        "ruleName": "AvoidDebugStatements",
        "category": "Performance",
        "url": "https://pmd.github.io/pmd-6.55.0/pmd_rules_apex_performance.html#avoiddebugstatements",
        "message": "\nAvoid debug statements since they impact on performance\n"
      },
      {
        "line": 90,
        "column": 36,
        "endLine": 90,
        "endColumn": 38,
        "severity": 5,
        "ruleName": "UnusedLocalVariable",
        "category": "Best Practices",
        "url": "https://pmd.github.io/pmd-6.55.0/pmd_rules_apex_bestpractices.html#unusedlocalvariable",
        "message": "\nVariable 'lcr' defined but not used\n"
      },
      {
        "line": 136,
        "column": 31,
        "endLine": 145,
        "endColumn": 5,
        "severity": 3,
        "ruleName": "ExcessiveParameterList",
        "category": "Design",
        "url": "https://pmd.github.io/pmd-6.55.0/pmd_rules_apex_design.html#excessiveparameterlist",
        "message": "\nAvoid long parameter lists.\n"
      }
    ]
  }
]
